grasp_env_handler/__init__.py
grasp_env_handler/cli.py
grasp_env_handler/env.py
grasp_env_handler/repo.py
grasp_env_handler-0.1.3.dist-info/METADATA
grasp_env_handler-0.1.3.dist-info/WHEEL
grasp_env_handler-0.1.3.dist-info/entry_points.txt
grasp_env_handler-0.1.3.dist-info/top_level.txt
grasp_env_handler-0.1.3.dist-info/RECORD
