Metadata-Version: 2.4
Name: grasp-env-handler
Version: 0.1.3
Summary: A utility for managing .env files using Google Cloud Secret Manager
Requires-Python: >=3.10
Requires-Dist: gitpython>=3.1.44
Requires-Dist: google-cloud-secret-manager>=2.23.3
Requires-Dist: python-dotenv>=1.1.0
Requires-Dist: rich>=14.0.0
Requires-Dist: typer>=0.15.3
Requires-Dist: click==8.1.7
